pytiingo/__init__.py
pytiingo/rest/__init__.py
pytiingo/rest/client.py
pytiingo/rest/configuration.py
pytiingo/rest/utils.py
pytiingo/rest/api_models/__init__.py
pytiingo/rest/api_models/base_api.py
pytiingo/rest/api_models/crypto_api.py
pytiingo/rest/api_models/eod_api.py
pytiingo/rest/api_models/forex_api.py
pytiingo/rest/api_models/fundamentals_api.py
pytiingo/rest/api_models/iex_api.py
pytiingo/rest/api_models/news_api.py
pytiingo/rest/http/__init__.py
pytiingo/rest/http/http_client.py
pytiingo/rest/http/http_request.py
pytiingo/rest/http/http_response.py
tests/__init__.py
pytiingo-0.0.1.dist-info/LICENSE
pytiingo-0.0.1.dist-info/METADATA
pytiingo-0.0.1.dist-info/WHEEL
pytiingo-0.0.1.dist-info/top_level.txt
pytiingo-0.0.1.dist-info/RECORD
