Metadata-Version: 2.1
Name: pytiingo
Version: 0.0.1
Summary: Python SDK for Tiingo Financial Markets API
Home-page: https://github.com/philipk19238/pytiingo
Author: Philip Kung
Author-email: pkung67@utexas.edu
License: UNKNOWN
Platform: UNKNOWN
Requires-Dist: requests
Requires-Dist: python-dotenv
Requires-Dist: pandas
Requires-Dist: pydantic
